[
  {
    "deutsch": "pfanne",
    "albanisch": "tigan",
    "repetitions": 0,
    "interval": 1,
    "easeFactor": 2.5,
    "nextReviewDate": "2025-06-04",
    "correctInErrorQuizCount": 0
  },
  {
    "deutsch": "nein",
    "albanisch": "jo",
    "repetitions": 0,
    "interval": 1,
    "easeFactor": 2.5,
    "nextReviewDate": "2025-06-04",
    "correctInErrorQuizCount": 0
  },
  {
    "deutsch": "rauchen",
    "albanisch": "pi duhan",
    "repetitions": 0,
    "interval": 1,
    "easeFactor": 2.5,
    "nextReviewDate": "2025-06-04",
    "correctInErrorQuizCount": 0
  }
]